MANIFEST.in
README.txt
setup.py
chatboteora.egg-info/PKG-INFO
chatboteora.egg-info/SOURCES.txt
chatboteora.egg-info/dependency_links.txt
chatboteora.egg-info/entry_points.txt
chatboteora.egg-info/requires.txt
chatboteora.egg-info/top_level.txt
my_app/Leicester_City.png
my_app/__init__.py
my_app/tests.py
my_app/__pycache__/__init__.cpython-35.pyc
my_app/scripts/__init__.py
my_app/scripts/count_ops.py
my_app/scripts/evaluate.py
my_app/scripts/graph_pb2tb.py
my_app/scripts/label_image.py
my_app/scripts/quantize_graph.py
my_app/scripts/retrain.py
my_app/scripts/show_image.py