Metadata-Version: 1.1
Name: chatboteora
Version: 0.2
Summary: Chatbot
Home-page: https://github.com/Lehsuby/chatbotEORA
Author: Lehsuby
Author-email: UNKNOWN
License: UNKNOWN
Platform: UNKNOWN
Classifier: Programming Language :: Python :: 3.5
